[
  {
    "Name": "AldOg",
    "Twitter Handle": "@AldOG69497571",
    "Twitter URL": "https://twitter.com/@AldOG69497571",
    "Profile": "Aladdin community supporter in Discord",
    "Contrib URL": "https://twitter.com/aldog69497571/status/1573614493699133440"
  },
  {
    "Name": "Cody White",
    "Twitter Handle": "@cewh1te",
    "Twitter URL": "https://twitter.com/@cewh1te",
    "Profile": "Trader / investor @cmsholdings",
    "Contrib URL": "https://twitter.com/aladdindao/status/1574850053965025285"
  },
  {
    "Name": "CryptoProphet",
    "Twitter Handle": "@CryptoProphet01",
    "Twitter URL": "https://twitter.com/@CryptoProphet01",
    "Profile": "DeFi YouTuber",
    "Contrib URL": "https://www.youtube.com/watch?v=2PhxgGZ8V5o"
  },
  {
    "Name": "Curvecap",
    "Twitter Handle": "@CurveCap",
    "Twitter URL": "https://twitter.com/@CurveCap",
    "Profile": "Curve Market Cap newsletter author and YouTuber",
    "Contrib URL": "https://www.youtube.com/watch?v=1TBOpdWDh-g"
  },
  {
    "Name": "DeFi Advisoor",
    "Twitter Handle": "@DAdvisoor",
    "Twitter URL": "https://twitter.com/@DAdvisoor",
    "Profile": "Another Day in Crypto newsletter author, DeFi influencer",
    "Contrib URL": "https://defiadvisoor.substack.com/p/another-day-in-crypto-84-aladdin"
  },
  {
    "Name": "DeFi Dad",
    "Twitter Handle": "@DeFi_Dad",
    "Twitter URL": "https://twitter.com/@DeFi_Dad",
    "Profile": "DeFi super-user and advisor, partner at @4RCapital",
    "Contrib URL": "https://twitter.com/DeFi_Dad/status/1569660032798846977"
  },
  {
    "Name": "DeFi Scout",
    "Twitter Handle": "@cryptobeijing",
    "Twitter URL": "https://twitter.com/@cryptobeijing",
    "Profile": "Chinese language DeFi content",
    "Contrib URL": "https://twitter.com/cryptobeijing/status/1577507927329746944"
  },
  {
    "Name": "Dilligent Deer",
    "Twitter Handle": "@diligentdeer",
    "Twitter URL": "https://twitter.com/@diligentdeer",
    "Profile": "Research, analysis, insights, opinions",
    "Contrib URL": "https://twitter.com/diligentdeer/status/1577596841532661760"
  },
  {
    "Name": "Escaped Wagie",
    "Twitter Handle": "@EscapedWagie",
    "Twitter URL": "https://twitter.com/@EscapedWagie",
    "Profile": "Full time speculator / yield farmer",
    "Contrib URL": "https://twitter.com/EscapedWagie/status/1575988805727064066"
  },
  {
    "Name": "Forgiven",
    "Twitter Handle": "@forgivenever",
    "Twitter URL": "https://twitter.com/@forgivenever",
    "Profile": "AladdinDAO Boule member, Chinese DeFi influencer",
    "Contrib URL": "https://twitter.com/forgivenever/status/1522232826493476864"
  },
  {
    "Name": "Haowi",
    "Twitter Handle": "@HaowiWang",
    "Twitter URL": "https://twitter.com/@HaowiWang",
    "Profile": "Chinese Curve influencer",
    "Contrib URL": "https://twitter.com/HaowiWang/status/1559667896929771520"
  },
  {
    "Name": "Kingmaker Podcast",
    "Twitter Handle": "@Kngmkrpod",
    "Twitter URL": "https://twitter.com/@Kngmkrpod",
    "Profile": "DeFi YouTuber and podcaster focused on CRV CVX and FXS",
    "Contrib URL": "https://twitter.com/Kngmkrpod/status/1555366084705804288"
  },
  {
    "Name": "Kmets",
    "Twitter Handle": "@kmets_",
    "Twitter URL": "https://twitter.com/@kmets_",
    "Profile": "DeFi writer, educator, community member",
    "Contrib URL": "https://twitter.com/kmets_/status/1577318391861415936"
  },
  {
    "Name": "Laughingfox",
    "Twitter Handle": "@laughingfoxeth",
    "Twitter URL": "https://twitter.com/@laughingfoxeth",
    "Profile": "DeFi threadoor",
    "Contrib URL": "https://twitter.com/laughingfoxeth/status/1573062953343107072"
  },
  {
    "Name": "MarcoV",
    "Twitter Handle": "@marcov_91",
    "Twitter URL": "https://twitter.com/@marcov_91",
    "Profile": "Data scientist",
    "Contrib URL": "https://dune.com/Marcov/clever"
  },
  {
    "Name": "MarsDAO",
    "Twitter Handle": "@MarsDAO_",
    "Twitter URL": "https://twitter.com/@MarsDAO_",
    "Profile": "Exploring Web3",
    "Contrib URL": "https://twitter.com/MarsDAO_/status/1575304197527859200"
  },
  {
    "Name": "Martin Krung",
    "Twitter Handle": "@martinkrung",
    "Twitter URL": "https://twitter.com/@martinkrung",
    "Profile": "Cryptonative web site and newsletter, AladdinDAO contributor",
    "Contrib URL": "https://twitter.com/martinkrung/status/1577299614356705281"
  },
  {
    "Name": "MetaCVX",
    "Twitter Handle": "@MetaversoXRP",
    "Twitter URL": "https://twitter.com/@MetaversoXRP",
    "Profile": "CVX cash flow!",
    "Contrib URL": "https://twitter.com/MetaversoXRP/status/1559654728690180096"
  },
  {
    "Name": "Moon Frog",
    "Twitter Handle": "@CFrogE1",
    "Twitter URL": "https://twitter.com/@CFrogE1",
    "Profile": "CRV and CVX maxi, influencer and meme craftsman",
    "Contrib URL": "https://twitter.com/CFrogE1/status/1572379753025343489"
  },
  {
    "Name": "Mr Masa",
    "Twitter Handle": "@0xmrmasa88",
    "Twitter URL": "https://twitter.com/@0xmrmasa88",
    "Profile": "Tech entrepreneur, YouTuber, AladdinDAO Boule member",
    "Contrib URL": "https://www.youtube.com/watch?v=wXcs51eDcEE"
  },
  {
    "Name": "mrblock",
    "Twitter Handle": "@mrblocktw",
    "Twitter URL": "https://twitter.com/@mrblocktw",
    "Profile": "Mandarin Chinese crypto YouTuber",
    "Contrib URL": "https://www.youtube.com/watch?v=o606XfyVOFg"
  },
  {
    "Name": "RetiredOnCrypto",
    "Twitter Handle": "@jagermario",
    "Twitter URL": "https://twitter.com/@jagermario",
    "Profile": "Project Management & World Traveler - DeFi Maxi, Adventurer in the Cryptoverse looking for real yield. Found the $CVX flywheel and never looked back.",
    "Contrib URL": "https://twitter.com/JagerMario/status/1577827684465385473"
  },
  {
    "Name": "Subli",
    "Twitter Handle": "@Subli_Defi",
    "Twitter URL": "https://twitter.com/@Subli_Defi",
    "Profile": "AladdinDAO Genie, DeFi threadooor, YouTuber",
    "Contrib URL": "https://sublidefi.notion.site/CLever-f9bc45ccea7a4a6583cd9d785ffb73e9"
  },
  {
    "Name": "Tao",
    "Twitter Handle": "@taowang1",
    "Twitter URL": "https://twitter.com/@taowang1",
    "Profile": "Web3 builder; Member of DeveloperDAO, BitEye, Alchemy",
    "Contrib URL": ""
  },
  {
    "Name": "Tiger VC Dao",
    "Twitter Handle": "@TigerVCDAO",
    "Twitter URL": "https://twitter.com/@TigerVCDAO",
    "Profile": "A decentralized VC that belongs to us all",
    "Contrib URL": "https://twitter.com/TigerVCDAO/status/1585233130419818496"
  },
  {
    "Name": "ZrowGz",
    "Twitter Handle": "@zrowgz",
    "Twitter URL": "https://twitter.com/@zrowgz",
    "Profile": "Decentralize This! newsletter author",
    "Contrib URL": "https://twitter.com/CurveCap/status/1559159648745410561"
  }
]
